none_shall_parse/__init__.py
none_shall_parse/dates.py
none_shall_parse/imeis.py
none_shall_parse/lists.py
none_shall_parse/parse.py
none_shall_parse/strings.py
none_shall_parse/types.py
none_shall_parse-0.6.1.dist-info/WHEEL
none_shall_parse-0.6.1.dist-info/METADATA
none_shall_parse-0.6.1.dist-info/RECORD
