Metadata-Version: 2.3
Name: none-shall-parse
Version: 0.6.1
Summary: Trinity Shared Python utilities.
Author: Andries Niemandt, Jan Badenhorst
Author-email: Andries Niemandt <andries.niemandt@trintel.co.za>, Jan Badenhorst <jan@trintel.co.za>
License: MIT
Classifier: Programming Language :: Python :: 3
Classifier: License :: OSI Approved :: MIT License
Classifier: Operating System :: OS Independent
Requires-Dist: pendulum
Requires-Dist: pytest>=8.0.0 ; extra == 'dev'
Requires-Dist: ruff>=0.12.3 ; extra == 'dev'
Requires-Dist: isort ; extra == 'dev'
Requires-Dist: flake8 ; extra == 'dev'
Requires-Dist: uv-build ; extra == 'dev'
Requires-Python: >=3.12
Project-URL: Homepage, https://github.com/trinity-telecomms/tpu
Project-URL: Issues, https://github.com/trinity-telecomms/tpu/issues
Provides-Extra: dev
